kaggler/__init__.py
kaggler/const.py
kaggler/data_io.py
kaggler/util.c
kaggler/util.cpython-38-darwin.so
kaggler/util.pxd
kaggler/util.pyx
kaggler/ensemble/__init__.py
kaggler/ensemble/linear.py
kaggler/feature_selection/__init__.py
kaggler/feature_selection/feature_selection.py
kaggler/metrics/__init__.py
kaggler/metrics/classification.py
kaggler/metrics/regression.py
kaggler/model/__init__.py
kaggler/model/automl.py
kaggler/model/nn.py
kaggler/online_model/__init__.py
kaggler/online_model/_tree.c
kaggler/online_model/_tree.cpython-38-darwin.so
kaggler/online_model/_tree.pyx
kaggler/online_model/classification_tree.py
kaggler/online_model/fm.c
kaggler/online_model/fm.cpython-38-darwin.so
kaggler/online_model/fm.pyx
kaggler/online_model/ftrl.c
kaggler/online_model/ftrl.cpython-38-darwin.so
kaggler/online_model/ftrl.pyx
kaggler/online_model/nn.c
kaggler/online_model/nn.cpython-38-darwin.so
kaggler/online_model/nn.pyx
kaggler/online_model/nn_h2.c
kaggler/online_model/nn_h2.cpython-38-darwin.so
kaggler/online_model/nn_h2.pyx
kaggler/online_model/sgd.c
kaggler/online_model/sgd.cpython-38-darwin.so
kaggler/online_model/sgd.pyx
kaggler/online_model/murmurhash/MurmurHash3.cpp
kaggler/online_model/murmurhash/MurmurHash3.h
kaggler/preprocessing/__init__.py
kaggler/preprocessing/autoencoder.py
kaggler/preprocessing/categorical.py
kaggler/preprocessing/const.py
kaggler/preprocessing/numerical.py
Kaggler-0.9.11.dist-info/LICENSE
Kaggler-0.9.11.dist-info/METADATA
Kaggler-0.9.11.dist-info/WHEEL
Kaggler-0.9.11.dist-info/top_level.txt
Kaggler-0.9.11.dist-info/RECORD
