Metadata-Version: 2.1
Name: Kaggler
Version: 0.9.11
Summary: Code for Kaggle Data Science Competitions.
Home-page: https://github.com/jeongyoonlee/Kaggler
Author: Jeong-Yoon Lee
Author-email: jeongyoon.lee1@gmail.com
License: LICENSE
Platform: UNKNOWN
Requires-Python: >=3.6
License-File: LICENSE
Requires-Dist: tensorflow
Requires-Dist: cython
Requires-Dist: hyperopt
Requires-Dist: lightgbm
Requires-Dist: ml-metrics
Requires-Dist: statsmodels
Requires-Dist: matplotlib
Requires-Dist: kaggle
Requires-Dist: xgboost
